<tree-map>
  <entry>
    <string>Animus</string>
    <redsun.entities.Armor>
      <id>Animus</id>
      <imgId>Animus</imgId>
      <screenX>0</screenX>
      <screenY>0</screenY>
      <equiptable>false</equiptable>
      <equipted>false</equipted>
      <type>ARMOR</type>
      <effects>
        <entry>
          <redsun.entities.Character_-Stat>STRENGTH</redsun.entities.Character_-Stat>
          <int>4</int>
        </entry>
        <entry>
          <redsun.entities.Character_-Stat>ELEMENTAL_ATTACK</redsun.entities.Character_-Stat>
          <int>1</int>
        </entry>
        <entry>
          <redsun.entities.Character_-Stat>DEFENSE</redsun.entities.Character_-Stat>
          <int>8</int>
        </entry>
        <entry>
          <redsun.entities.Character_-Stat>ELEMENTAL_DEFENSE</redsun.entities.Character_-Stat>
          <int>0</int>
        </entry>
        <entry>
          <redsun.entities.Character_-Stat>WEAPON_SKILL</redsun.entities.Character_-Stat>
          <int>0</int>
        </entry>
        <entry>
          <redsun.entities.Character_-Stat>AGILITY</redsun.entities.Character_-Stat>
          <int>10</int>
        </entry>
        <entry>
          <redsun.entities.Character_-Stat>INTELLIGENCE</redsun.entities.Character_-Stat>
          <int>5</int>
        </entry>
        <entry>
          <redsun.entities.Character_-Stat>HEALTH</redsun.entities.Character_-Stat>
          <int>1</int>
        </entry>
        <entry>
          <redsun.entities.Character_-Stat>CRIT</redsun.entities.Character_-Stat>
          <int>21</int>
        </entry>
      </effects>
      <x>0</x>
      <y>0</y>
      <value>0</value>
      <level>0</level>
      <armor>30</armor>
      <earmor>28</earmor>
      <weight>12</weight>
      <part>ACCESSORY</part>
    </redsun.entities.Armor>
  </entry>
  <entry>
    <string>Axe</string>
    <redsun.entities.Weapon>
      <id>Axe</id>
      <imgId>Axe</imgId>
      <screenX>0</screenX>
      <screenY>0</screenY>
      <equiptable>false</equiptable>
      <equipted>false</equipted>
      <type>WEAPON</type>
      <effects>
        <entry>
          <redsun.entities.Character_-Stat>STRENGTH</redsun.entities.Character_-Stat>
          <int>4</int>
        </entry>
        <entry>
          <redsun.entities.Character_-Stat>ELEMENTAL_ATTACK</redsun.entities.Character_-Stat>
          <int>1</int>
        </entry>
        <entry>
          <redsun.entities.Character_-Stat>DEFENSE</redsun.entities.Character_-Stat>
          <int>1</int>
        </entry>
        <entry>
          <redsun.entities.Character_-Stat>ELEMENTAL_DEFENSE</redsun.entities.Character_-Stat>
          <int>1</int>
        </entry>
        <entry>
          <redsun.entities.Character_-Stat>WEAPON_SKILL</redsun.entities.Character_-Stat>
          <int>2</int>
        </entry>
        <entry>
          <redsun.entities.Character_-Stat>AGILITY</redsun.entities.Character_-Stat>
          <int>3</int>
        </entry>
        <entry>
          <redsun.entities.Character_-Stat>INTELLIGENCE</redsun.entities.Character_-Stat>
          <int>7</int>
        </entry>
        <entry>
          <redsun.entities.Character_-Stat>HEALTH</redsun.entities.Character_-Stat>
          <int>1</int>
        </entry>
        <entry>
          <redsun.entities.Character_-Stat>CRIT</redsun.entities.Character_-Stat>
          <int>12</int>
        </entry>
      </effects>
      <x>0</x>
      <y>0</y>
      <value>0</value>
      <level>0</level>
      <attack>22</attack>
      <elementa>0</elementa>
      <weight>18</weight>
      <wclass>AXE</wclass>
    </redsun.entities.Weapon>
  </entry>
  <entry>
    <string>LightSaber</string>
    <redsun.entities.Weapon>
      <id>LightSaber</id>
      <imgId>DefaultItem</imgId>
      <screenX>0</screenX>
      <screenY>0</screenY>
      <equiptable>false</equiptable>
      <equipted>false</equipted>
      <type>WEAPON</type>
      <effects>
        <entry>
          <redsun.entities.Character_-Stat>STRENGTH</redsun.entities.Character_-Stat>
          <int>0</int>
        </entry>
        <entry>
          <redsun.entities.Character_-Stat>ELEMENTAL_ATTACK</redsun.entities.Character_-Stat>
          <int>0</int>
        </entry>
        <entry>
          <redsun.entities.Character_-Stat>DEFENSE</redsun.entities.Character_-Stat>
          <int>0</int>
        </entry>
        <entry>
          <redsun.entities.Character_-Stat>ELEMENTAL_DEFENSE</redsun.entities.Character_-Stat>
          <int>0</int>
        </entry>
        <entry>
          <redsun.entities.Character_-Stat>WEAPON_SKILL</redsun.entities.Character_-Stat>
          <int>0</int>
        </entry>
        <entry>
          <redsun.entities.Character_-Stat>AGILITY</redsun.entities.Character_-Stat>
          <int>0</int>
        </entry>
        <entry>
          <redsun.entities.Character_-Stat>INTELLIGENCE</redsun.entities.Character_-Stat>
          <int>0</int>
        </entry>
        <entry>
          <redsun.entities.Character_-Stat>HEALTH</redsun.entities.Character_-Stat>
          <int>0</int>
        </entry>
        <entry>
          <redsun.entities.Character_-Stat>CRIT</redsun.entities.Character_-Stat>
          <int>0</int>
        </entry>
      </effects>
      <x>0</x>
      <y>0</y>
      <value>0</value>
      <level>0</level>
      <attack>123</attack>
      <elementa>324</elementa>
      <weight>0</weight>
      <wclass>SWORD</wclass>
    </redsun.entities.Weapon>
  </entry>
  <entry>
    <string>Sword</string>
    <redsun.entities.Weapon>
      <id>Sword</id>
      <imgId>DefaultItem</imgId>
      <screenX>0</screenX>
      <screenY>0</screenY>
      <equiptable>false</equiptable>
      <equipted>false</equipted>
      <type>WEAPON</type>
      <effects>
        <entry>
          <redsun.entities.Character_-Stat>STRENGTH</redsun.entities.Character_-Stat>
          <int>8</int>
        </entry>
        <entry>
          <redsun.entities.Character_-Stat>ELEMENTAL_ATTACK</redsun.entities.Character_-Stat>
          <int>5</int>
        </entry>
        <entry>
          <redsun.entities.Character_-Stat>DEFENSE</redsun.entities.Character_-Stat>
          <int>0</int>
        </entry>
        <entry>
          <redsun.entities.Character_-Stat>ELEMENTAL_DEFENSE</redsun.entities.Character_-Stat>
          <int>0</int>
        </entry>
        <entry>
          <redsun.entities.Character_-Stat>WEAPON_SKILL</redsun.entities.Character_-Stat>
          <int>2</int>
        </entry>
        <entry>
          <redsun.entities.Character_-Stat>AGILITY</redsun.entities.Character_-Stat>
          <int>1</int>
        </entry>
        <entry>
          <redsun.entities.Character_-Stat>INTELLIGENCE</redsun.entities.Character_-Stat>
          <int>3</int>
        </entry>
        <entry>
          <redsun.entities.Character_-Stat>HEALTH</redsun.entities.Character_-Stat>
          <int>6</int>
        </entry>
        <entry>
          <redsun.entities.Character_-Stat>CRIT</redsun.entities.Character_-Stat>
          <int>33</int>
        </entry>
      </effects>
      <x>0</x>
      <y>0</y>
      <value>0</value>
      <level>0</level>
      <attack>10</attack>
      <elementa>5</elementa>
      <weight>8</weight>
      <wclass>SWORD</wclass>
    </redsun.entities.Weapon>
  </entry>
  <entry>
    <string>what</string>
    <redsun.entities.Item>
      <id>what</id>
      <imgId>Spear</imgId>
      <screenX>0</screenX>
      <screenY>0</screenY>
      <equiptable>false</equiptable>
      <equipted>false</equipted>
      <type>KEYITEM</type>
      <effects>
        <entry>
          <redsun.entities.Character_-Stat>STRENGTH</redsun.entities.Character_-Stat>
          <int>0</int>
        </entry>
        <entry>
          <redsun.entities.Character_-Stat>ELEMENTAL_ATTACK</redsun.entities.Character_-Stat>
          <int>0</int>
        </entry>
        <entry>
          <redsun.entities.Character_-Stat>DEFENSE</redsun.entities.Character_-Stat>
          <int>47</int>
        </entry>
        <entry>
          <redsun.entities.Character_-Stat>ELEMENTAL_DEFENSE</redsun.entities.Character_-Stat>
          <int>0</int>
        </entry>
        <entry>
          <redsun.entities.Character_-Stat>WEAPON_SKILL</redsun.entities.Character_-Stat>
          <int>0</int>
        </entry>
        <entry>
          <redsun.entities.Character_-Stat>AGILITY</redsun.entities.Character_-Stat>
          <int>60</int>
        </entry>
        <entry>
          <redsun.entities.Character_-Stat>INTELLIGENCE</redsun.entities.Character_-Stat>
          <int>0</int>
        </entry>
        <entry>
          <redsun.entities.Character_-Stat>HEALTH</redsun.entities.Character_-Stat>
          <int>0</int>
        </entry>
        <entry>
          <redsun.entities.Character_-Stat>CRIT</redsun.entities.Character_-Stat>
          <int>0</int>
        </entry>
      </effects>
      <x>0</x>
      <y>0</y>
      <value>0</value>
      <level>0</level>
    </redsun.entities.Item>
  </entry>
</tree-map>